jinjitest/__init__.py
jinjitest-1.3.1.dist-info/licenses/LICENSE
jinjitest-1.3.1.dist-info/METADATA
jinjitest-1.3.1.dist-info/WHEEL
jinjitest-1.3.1.dist-info/top_level.txt
jinjitest-1.3.1.dist-info/RECORD
